geri_dir/__init__.py
geri_dir/basic.py
geri_personal_module-0.0.1.dist-info/METADATA
geri_personal_module-0.0.1.dist-info/WHEEL
geri_personal_module-0.0.1.dist-info/licenses/LICENCE.txt
geri_personal_module-0.0.1.dist-info/RECORD
